gopup/__init__.py
gopup/my_fun.py
gopup/economic/__init__.py
gopup/economic/cons.py
gopup/economic/marco_cn.py
gopup/economic/shibor.py
gopup/event/__init__.py
gopup/event/area_baidu.py
gopup/event/cons.py
gopup/event/covid.py
gopup/event/history_daily.py
gopup/event/hot_list.py
gopup/fortune/__init__.py
gopup/fortune/cons.py
gopup/fortune/franchise.py
gopup/fortune/itjuzi.py
gopup/index/__init__.py
gopup/index/baidu_decrypt.py
gopup/index/cons.py
gopup/index/errors.py
gopup/index/google_request.py
gopup/index/index_baidu.py
gopup/index/index_google.py
gopup/index/index_sogou.py
gopup/index/index_toutiao.py
gopup/index/index_weibo.py
gopup/life/__init__.py
gopup/life/charity.py
gopup/life/game.py
gopup/life/oil.py
gopup/life/train.py
gopup/life/university.py
gopup/mcn/__init__.py
gopup/mcn/cons.py
gopup/mcn/crawler_weibo.py
gopup/mcn/star.py
gopup/mcn/weibo.py
gopup/movie/__init__.py
gopup/movie/cons.py
gopup/movie/movie.py
gopup/pro/__init__.py
gopup/pro/client.py
gopup/pro/pro_data.py
gopup/stock/__init__.py
gopup/stock/classifying.py
gopup/stock/cons.py
gopup/stock/fund.py
gopup/utils/__init__.py
gopup/utils/date_utils.py
gopup/utils/rest_agent.py
gopup/utils/url_utils.py
gopup/utils/utils.py
gopup/utils/utils_pass.py
gopup/wechat/__init__.py
gopup-0.3.8.dist-info/METADATA
gopup-0.3.8.dist-info/WHEEL
gopup-0.3.8.dist-info/top_level.txt
gopup-0.3.8.dist-info/RECORD
