Metadata-Version: 2.1
Name: gopup
Version: 0.3.8
Summary: GoPUP database
Home-page: https://github.com/justinzm/gopup
Author: Justin ZM
Author-email: 3907721@qq.com
Maintainer: Justin ZM
Maintainer-email: 3907721@qq.com
License: MIT
Platform: all
Requires-Dist: requests
Requires-Dist: pandas
Requires-Dist: demjson
Requires-Dist: jsonpath
Requires-Dist: bs4
Requires-Dist: Pillow
Requires-Dist: matplotlib
Requires-Dist: xlrd
Requires-Dist: pyexecjs
Requires-Dist: pyquery
Requires-Dist: tqdm
Requires-Dist: pycryptodome
